README.txt
setup.py
docs/HISTORY.txt
teamrubber/__init__.py
teamrubber.googlechart.egg-info/PKG-INFO
teamrubber.googlechart.egg-info/SOURCES.txt
teamrubber.googlechart.egg-info/dependency_links.txt
teamrubber.googlechart.egg-info/entry_points.txt
teamrubber.googlechart.egg-info/namespace_packages.txt
teamrubber.googlechart.egg-info/not-zip-safe
teamrubber.googlechart.egg-info/requires.txt
teamrubber.googlechart.egg-info/top_level.txt
teamrubber/googlechart/__init__.py
teamrubber/googlechart/chart.py
teamrubber/googlechart/configure.zcml
teamrubber/googlechart/dtml/googlechart.png
teamrubber/googlechart/dtml/teamrubber_googlechartAdd.dtml
