Metadata-Version: 1.0
Name: teamrubber.googlechart
Version: 0.1
Summary: Provides a Zope object that acts as a wrapper for pygooglechart
Home-page: http://www.teamrubber.com
Author: Richard Wilson
Author-email: team@teamrubber.com
License: GPL
Keywords: zope plone googlechart
Platform: UNKNOWN
Classifier: License :: OSI Approved :: GNU General Public License (GPL)
Classifier: Programming Language :: Python
Classifier: Topic :: Software Development :: Libraries :: Python Modules
Classifier: Development Status :: 2 - Pre-Alpha
Classifier: Intended Audience :: Developers
Classifier: Framework :: Zope2
Classifier: Framework :: Plone
